kovapy.py
kovapy-0.0.1.dist-info/LICENSE
kovapy-0.0.1.dist-info/METADATA
kovapy-0.0.1.dist-info/WHEEL
kovapy-0.0.1.dist-info/top_level.txt
kovapy-0.0.1.dist-info/RECORD
