Metadata-Version: 2.1
Name: kovapy
Version: 0.0.1
Summary: Kova Robotics Utilities Package. This is how I take over the world.
Home-page: http://www.kova.co.za
Author: William Van Loggerenberg
Author-email: will@kova.co.za
License: UNKNOWN
Platform: UNKNOWN
Requires-Dist: slackclient (~=2.5.0)
